datarefiner/__init__.py
datarefiner/ml/__init__.py
datarefiner/ml/label.py
datarefiner/ml/scaler.py
datarefiner/ts/__init__.py
datarefiner/ts/differencing.py
datarefiner/ts/window.py
datarefiner-0.1.0.dist-info/LICENSE
datarefiner-0.1.0.dist-info/METADATA
datarefiner-0.1.0.dist-info/WHEEL
datarefiner-0.1.0.dist-info/top_level.txt
datarefiner-0.1.0.dist-info/RECORD
