Metadata-Version: 2.1
Name: datarefiner
Version: 0.1.0
Summary: DataRefiner: An Advanced Toolkit for Data Transformation and Processing
Home-page: https://github.com/thieu1995/datarefiner
Author: Thieu
Author-email: nguyenthieu2102@gmail.com
License: GPLv3
Project-URL: Documentation, https://datarefiner.readthedocs.io/
Project-URL: Source Code, https://github.com/thieu1995/datarefiner
Project-URL: Bug Tracker, https://github.com/thieu1995/datarefiner/issues
Project-URL: Change Log, https://github.com/thieu1995/datarefiner/blob/master/ChangeLog.md
Project-URL: Forum, https://t.me/+fRVCJGuGJg1mNDg1
Keywords: Data refining,Data tidying,Data munging,Data grooming,Data optimization,Data formatting,Data structuringData filtering,Data cleansing,Data standardization,Data enrichment,Feature engineering,Data wrangling,Data transformation,Data scaling,Data normalizationData preprocessing,Data preparation,Data analysis
Classifier: Development Status :: 5 - Production/Stable
Classifier: Intended Audience :: Developers
Classifier: Intended Audience :: Education
Classifier: Intended Audience :: Information Technology
Classifier: Intended Audience :: Science/Research
Classifier: License :: OSI Approved :: GNU General Public License v3 (GPLv3)
Classifier: Natural Language :: English
Classifier: Programming Language :: Python :: 3
Classifier: Programming Language :: Python :: 3.8
Classifier: Programming Language :: Python :: 3.9
Classifier: Programming Language :: Python :: 3.10
Classifier: Programming Language :: Python :: 3.11
Classifier: Programming Language :: Python :: 3.12
Classifier: Topic :: System :: Benchmark
Classifier: Topic :: Scientific/Engineering
Classifier: Topic :: Scientific/Engineering :: Mathematics
Classifier: Topic :: Scientific/Engineering :: Artificial Intelligence
Classifier: Topic :: Scientific/Engineering :: Information Analysis
Classifier: Topic :: Scientific/Engineering :: Visualization
Classifier: Topic :: Scientific/Engineering :: Bio-Informatics
Classifier: Topic :: Software Development :: Build Tools
Classifier: Topic :: Software Development :: Libraries
Classifier: Topic :: Software Development :: Libraries :: Python Modules
Classifier: Topic :: Utilities
Requires-Python: >=3.8
License-File: LICENSE
Requires-Dist: numpy >=1.17.1
Requires-Dist: scipy >=1.7.1
Requires-Dist: scikit-learn >=1.0.2
Requires-Dist: pandas >=1.3.5
Requires-Dist: permetrics >=2.0.0
Provides-Extra: dev
Requires-Dist: pytest >=7.0 ; extra == 'dev'
Requires-Dist: pytest-cov ==4.0.0 ; extra == 'dev'
Requires-Dist: flake8 >=4.0.1 ; extra == 'dev'
